{
    "QQQ": {
        "entry": 598.42,
        "qty": 16,
        "side": "sell",
        "sl": 616.3725999999999,
        "tp": 568.4989999999999,
        "entry_time": "2025-09-19T18:46:54.117500",
        "last_update": "2025-11-14T18:42:12.159829"
    },
    "GLD": {
        "entry": 377.96,
        "qty": 25,
        "side": "sell",
        "sl": 389.29879999999997,
        "tp": 359.06199999999995,
        "entry_time": "2025-11-10T18:49:39.364271",
        "last_update": "2025-11-14T18:42:12.781693"
    },
    "EFA": {
        "entry": 96.615,
        "qty": 98,
        "side": "sell",
        "sl": 99.51344999999999,
        "tp": 91.78424999999999,
        "entry_time": "2025-11-12T18:49:26.582411",
        "last_update": "2025-11-14T18:42:13.286473"
    },
    "EEM": {
        "entry": 54.905,
        "qty": 436,
        "side": "buy",
        "sl": 53.25785,
        "tp": 57.65025000000001,
        "entry_time": "2025-11-13T18:50:33.779937",
        "last_update": "2025-11-14T18:42:13.786375"
    }
}